{"Position":{"x":0.0,"y":0.0},"Size.Min":{"w":0.0,"h":0.0},"Size.Max":{"w":1.7976931348623157e308,"h":1.7976931348623157e308},"Margin":{"l":0.0,"t":0.0,"r":0.0,"b":0.0},"AddTrigDist":{"l":0.0,"t":0.0,"r":0.0,"b":0.0},"Flags":[],"StringMap":[],"Transform":{"Rotation":0.0,"Flip":[]},"UID":0,"Name":"<null>","Title":"","ToolTip":"","GIType":"GraphicsGroupItemCfg","Alignment":"AlignCenter","SizePolicy":"Preferred","ConnectionDirection":"Any","Items":[{"Position":{"x":20.0,"y":10.0},"Size.Min":{"w":0.0,"h":0.0},"Size.Max":{"w":1.7976931348623157e308,"h":1.7976931348623157e308},"Margin":{"l":0.0,"t":0.0,"r":0.0,"b":0.0},"AddTrigDist":{"l":0.0,"t":0.0,"r":0.0,"b":0.0},"Flags":["Moveable","SnapsToGridTopLeft","HandleState"],"StringMap":[],"Transform":{"Rotation":0.0,"Flip":[]},"UID":1,"Name":"Line","Title":"","ToolTip":"","GIType":"GraphicsLineItemCfg","Alignment":"AlignCenter","SizePolicy":"Preferred","ConnectionDirection":"Out","From":{"x":0.0,"y":0.0},"To":{"x":10.0,"y":10.0},"LineStyle":{"Width":1.0,"Style":"Solid","Cap":"Square","Join":"Bevel","Painter":{"P2Type":"OT_P2DStyR","Ref":"GraphicsItem Line Color"}}},{"Position":{"x":20.0,"y":10.0},"Size.Min":{"w":0.0,"h":0.0},"Size.Max":{"w":1.7976931348623157e308,"h":1.7976931348623157e308},"Margin":{"l":0.0,"t":0.0,"r":0.0,"b":0.0},"AddTrigDist":{"l":0.0,"t":0.0,"r":0.0,"b":0.0},"Flags":["Moveable","SnapsToGridTopLeft","HandleState"],"StringMap":[],"Transform":{"Rotation":0.0,"Flip":[]},"UID":2,"Name":"Line_1","Title":"","ToolTip":"","GIType":"GraphicsLineItemCfg","Alignment":"AlignCenter","SizePolicy":"Preferred","ConnectionDirection":"Out","From":{"x":0.0,"y":0.0},"To":{"x":40.0,"y":0.0},"LineStyle":{"Width":1.0,"Style":"Solid","Cap":"Square","Join":"Bevel","Painter":{"P2Type":"OT_P2DStyR","Ref":"GraphicsItem Line Color"}}},{"Position":{"x":50.0,"y":10.0},"Size.Min":{"w":0.0,"h":0.0},"Size.Max":{"w":1.7976931348623157e308,"h":1.7976931348623157e308},"Margin":{"l":0.0,"t":0.0,"r":0.0,"b":0.0},"AddTrigDist":{"l":0.0,"t":0.0,"r":0.0,"b":0.0},"Flags":["Moveable","SnapsToGridTopLeft","HandleState"],"StringMap":[],"Transform":{"Rotation":0.0,"Flip":[]},"UID":3,"Name":"Line_2","Title":"","ToolTip":"","GIType":"GraphicsLineItemCfg","Alignment":"AlignCenter","SizePolicy":"Preferred","ConnectionDirection":"Out","From":{"x":10.0,"y":0.0},"To":{"x":0.0,"y":10.0},"LineStyle":{"Width":1.0,"Style":"Solid","Cap":"Square","Join":"Bevel","Painter":{"P2Type":"OT_P2DStyR","Ref":"GraphicsItem Line Color"}}},{"Position":{"x":30.0,"y":20.0},"Size.Min":{"w":0.0,"h":0.0},"Size.Max":{"w":1.7976931348623157e308,"h":1.7976931348623157e308},"Margin":{"l":0.0,"t":0.0,"r":0.0,"b":0.0},"AddTrigDist":{"l":0.0,"t":0.0,"r":0.0,"b":0.0},"Flags":["Moveable","SnapsToGridTopLeft","HandleState"],"StringMap":[],"Transform":{"Rotation":0.0,"Flip":[]},"UID":4,"Name":"Line_3","Title":"","ToolTip":"","GIType":"GraphicsLineItemCfg","Alignment":"AlignCenter","SizePolicy":"Preferred","ConnectionDirection":"Out","From":{"x":20.0,"y":0.0},"To":{"x":0.0,"y":0.0},"LineStyle":{"Width":1.0,"Style":"Solid","Cap":"Square","Join":"Bevel","Painter":{"P2Type":"OT_P2DStyR","Ref":"GraphicsItem Line Color"}}},{"Position":{"x":30.0,"y":30.0},"Size.Min":{"w":0.0,"h":0.0},"Size.Max":{"w":1.7976931348623157e308,"h":1.7976931348623157e308},"Margin":{"l":0.0,"t":0.0,"r":0.0,"b":0.0},"AddTrigDist":{"l":0.0,"t":0.0,"r":0.0,"b":0.0},"Flags":["Moveable","SnapsToGridTopLeft","HandleState"],"StringMap":[],"Transform":{"Rotation":0.0,"Flip":[]},"UID":5,"Name":"Line_4","Title":"","ToolTip":"","GIType":"GraphicsLineItemCfg","Alignment":"AlignCenter","SizePolicy":"Preferred","ConnectionDirection":"Out","From":{"x":0.0,"y":0.0},"To":{"x":20.0,"y":0.0},"LineStyle":{"Width":1.0,"Style":"Solid","Cap":"Square","Join":"Bevel","Painter":{"P2Type":"OT_P2DStyR","Ref":"GraphicsItem Line Color"}}},{"Position":{"x":20.0,"y":30.0},"Size.Min":{"w":0.0,"h":0.0},"Size.Max":{"w":1.7976931348623157e308,"h":1.7976931348623157e308},"Margin":{"l":0.0,"t":0.0,"r":0.0,"b":0.0},"AddTrigDist":{"l":0.0,"t":0.0,"r":0.0,"b":0.0},"Flags":["Moveable","SnapsToGridTopLeft","HandleState"],"StringMap":[],"Transform":{"Rotation":0.0,"Flip":[]},"UID":6,"Name":"Line_5","Title":"","ToolTip":"","GIType":"GraphicsLineItemCfg","Alignment":"AlignCenter","SizePolicy":"Preferred","ConnectionDirection":"Out","From":{"x":10.0,"y":0.0},"To":{"x":0.0,"y":10.0},"LineStyle":{"Width":1.0,"Style":"Solid","Cap":"Square","Join":"Bevel","Painter":{"P2Type":"OT_P2DStyR","Ref":"GraphicsItem Line Color"}}},{"Position":{"x":50.0,"y":30.0},"Size.Min":{"w":0.0,"h":0.0},"Size.Max":{"w":1.7976931348623157e308,"h":1.7976931348623157e308},"Margin":{"l":0.0,"t":0.0,"r":0.0,"b":0.0},"AddTrigDist":{"l":0.0,"t":0.0,"r":0.0,"b":0.0},"Flags":["Moveable","SnapsToGridTopLeft","HandleState"],"StringMap":[],"Transform":{"Rotation":0.0,"Flip":[]},"UID":7,"Name":"Line_6","Title":"","ToolTip":"","GIType":"GraphicsLineItemCfg","Alignment":"AlignCenter","SizePolicy":"Preferred","ConnectionDirection":"Out","From":{"x":0.0,"y":0.0},"To":{"x":10.0,"y":10.0},"LineStyle":{"Width":1.0,"Style":"Solid","Cap":"Square","Join":"Bevel","Painter":{"P2Type":"OT_P2DStyR","Ref":"GraphicsItem Line Color"}}},{"Position":{"x":20.0,"y":40.0},"Size.Min":{"w":0.0,"h":0.0},"Size.Max":{"w":1.7976931348623157e308,"h":1.7976931348623157e308},"Margin":{"l":0.0,"t":0.0,"r":0.0,"b":0.0},"AddTrigDist":{"l":0.0,"t":0.0,"r":0.0,"b":0.0},"Flags":["Moveable","SnapsToGridTopLeft","HandleState"],"StringMap":[],"Transform":{"Rotation":0.0,"Flip":[]},"UID":8,"Name":"Line_7","Title":"","ToolTip":"","GIType":"GraphicsLineItemCfg","Alignment":"AlignCenter","SizePolicy":"Preferred","ConnectionDirection":"Out","From":{"x":0.0,"y":0.0},"To":{"x":40.0,"y":0.0},"LineStyle":{"Width":1.0,"Style":"Solid","Cap":"Square","Join":"Bevel","Painter":{"P2Type":"OT_P2DStyR","Ref":"GraphicsItem Line Color"}}},{"Position":{"x":10.0,"y":10.0},"Size.Min":{"w":0.0,"h":0.0},"Size.Max":{"w":1.7976931348623157e308,"h":1.7976931348623157e308},"Margin":{"l":0.0,"t":0.0,"r":0.0,"b":0.0},"AddTrigDist":{"l":0.0,"t":0.0,"r":0.0,"b":0.0},"Flags":["Moveable","SnapsToGridTopLeft","HandleState"],"StringMap":[],"Transform":{"Rotation":0.0,"Flip":[]},"UID":9,"Name":"Line_8","Title":"","ToolTip":"","GIType":"GraphicsLineItemCfg","Alignment":"AlignCenter","SizePolicy":"Preferred","ConnectionDirection":"Out","From":{"x":10.0,"y":0.0},"To":{"x":0.0,"y":0.0},"LineStyle":{"Width":1.0,"Style":"Solid","Cap":"Square","Join":"Bevel","Painter":{"P2Type":"OT_P2DFill","Color":{"r":255,"g":0,"b":0,"a":255}}}},{"Position":{"x":60.0,"y":10.0},"Size.Min":{"w":0.0,"h":0.0},"Size.Max":{"w":1.7976931348623157e308,"h":1.7976931348623157e308},"Margin":{"l":0.0,"t":0.0,"r":0.0,"b":0.0},"AddTrigDist":{"l":0.0,"t":0.0,"r":0.0,"b":0.0},"Flags":["Moveable","SnapsToGridTopLeft","HandleState"],"StringMap":[],"Transform":{"Rotation":0.0,"Flip":[]},"UID":10,"Name":"Line_9","Title":"","ToolTip":"","GIType":"GraphicsLineItemCfg","Alignment":"AlignCenter","SizePolicy":"Preferred","ConnectionDirection":"Out","From":{"x":0.0,"y":0.0},"To":{"x":10.0,"y":0.0},"LineStyle":{"Width":1.0,"Style":"Solid","Cap":"Square","Join":"Bevel","Painter":{"P2Type":"OT_P2DFill","Color":{"r":255,"g":0,"b":0,"a":255}}}},{"Position":{"x":10.0,"y":40.0},"Size.Min":{"w":0.0,"h":0.0},"Size.Max":{"w":1.7976931348623157e308,"h":1.7976931348623157e308},"Margin":{"l":0.0,"t":0.0,"r":0.0,"b":0.0},"AddTrigDist":{"l":0.0,"t":0.0,"r":0.0,"b":0.0},"Flags":["Moveable","SnapsToGridTopLeft","HandleState"],"StringMap":[],"Transform":{"Rotation":0.0,"Flip":[]},"UID":11,"Name":"Line_10","Title":"","ToolTip":"","GIType":"GraphicsLineItemCfg","Alignment":"AlignCenter","SizePolicy":"Preferred","ConnectionDirection":"Out","From":{"x":10.0,"y":0.0},"To":{"x":0.0,"y":0.0},"LineStyle":{"Width":1.0,"Style":"Solid","Cap":"Square","Join":"Bevel","Painter":{"P2Type":"OT_P2DFill","Color":{"r":255,"g":0,"b":0,"a":255}}}},{"Position":{"x":60.0,"y":40.0},"Size.Min":{"w":0.0,"h":0.0},"Size.Max":{"w":1.7976931348623157e308,"h":1.7976931348623157e308},"Margin":{"l":0.0,"t":0.0,"r":0.0,"b":0.0},"AddTrigDist":{"l":0.0,"t":0.0,"r":0.0,"b":0.0},"Flags":["Moveable","SnapsToGridTopLeft","HandleState"],"StringMap":[],"Transform":{"Rotation":0.0,"Flip":[]},"UID":12,"Name":"Line_11","Title":"","ToolTip":"","GIType":"GraphicsLineItemCfg","Alignment":"AlignCenter","SizePolicy":"Preferred","ConnectionDirection":"Out","From":{"x":0.0,"y":0.0},"To":{"x":10.0,"y":0.0},"LineStyle":{"Width":1.0,"Style":"Solid","Cap":"Square","Join":"Bevel","Painter":{"P2Type":"OT_P2DFill","Color":{"r":255,"g":0,"b":0,"a":255}}}},{"Position":{"x":60.0,"y":0.0},"Size.Min":{"w":0.0,"h":0.0},"Size.Max":{"w":1.7976931348623157e308,"h":1.7976931348623157e308},"Margin":{"l":0.0,"t":0.0,"r":0.0,"b":0.0},"AddTrigDist":{"l":0.0,"t":0.0,"r":0.0,"b":0.0},"Flags":["Moveable","Connectable","SnapsToGridTopLeft"],"StringMap":[],"Transform":{"Rotation":0.0,"Flip":[]},"UID":13,"Name":"NegativePole1","Title":"","ToolTip":"","GIType":"GraphicsEllipseItemCfg","Alignment":"AlignCenter","SizePolicy":"Preferred","ConnectionDirection":"Out","RadiusX":10.0,"RadiusY":10.0,"BackgroundPainter":{"P2Type":"OT_P2DStyR","Ref":"Transparent"},"Outline":{"Width":0.0,"Style":"Solid","Cap":"Square","Join":"Bevel","Painter":{"P2Type":"OT_P2DStyR","Ref":"Transparent"}}},{"Position":{"x":60.0,"y":30.0},"Size.Min":{"w":0.0,"h":0.0},"Size.Max":{"w":1.7976931348623157e308,"h":1.7976931348623157e308},"Margin":{"l":0.0,"t":0.0,"r":0.0,"b":0.0},"AddTrigDist":{"l":0.0,"t":0.0,"r":0.0,"b":0.0},"Flags":["Moveable","Connectable","SnapsToGridTopLeft"],"StringMap":[],"Transform":{"Rotation":0.0,"Flip":[]},"UID":14,"Name":"NegativePole2","Title":"","ToolTip":"","GIType":"GraphicsEllipseItemCfg","Alignment":"AlignCenter","SizePolicy":"Preferred","ConnectionDirection":"Out","RadiusX":10.0,"RadiusY":10.0,"BackgroundPainter":{"P2Type":"OT_P2DStyR","Ref":"Transparent"},"Outline":{"Width":0.0,"Style":"Solid","Cap":"Square","Join":"Bevel","Painter":{"P2Type":"OT_P2DStyR","Ref":"Transparent"}}},{"Position":{"x":0.0,"y":30.0},"Size.Min":{"w":0.0,"h":0.0},"Size.Max":{"w":1.7976931348623157e308,"h":1.7976931348623157e308},"Margin":{"l":0.0,"t":0.0,"r":0.0,"b":0.0},"AddTrigDist":{"l":0.0,"t":0.0,"r":0.0,"b":0.0},"Flags":["Moveable","Connectable","SnapsToGridTopLeft"],"StringMap":[],"Transform":{"Rotation":0.0,"Flip":[]},"UID":15,"Name":"PositivePole2","Title":"","ToolTip":"","GIType":"GraphicsEllipseItemCfg","Alignment":"AlignCenter","SizePolicy":"Preferred","ConnectionDirection":"Out","RadiusX":10.0,"RadiusY":10.0,"BackgroundPainter":{"P2Type":"OT_P2DStyR","Ref":"Transparent"},"Outline":{"Width":0.0,"Style":"Solid","Cap":"Square","Join":"Bevel","Painter":{"P2Type":"OT_P2DStyR","Ref":"Transparent"}}},{"Position":{"x":0.0,"y":0.0},"Size.Min":{"w":0.0,"h":0.0},"Size.Max":{"w":1.7976931348623157e308,"h":1.7976931348623157e308},"Margin":{"l":0.0,"t":0.0,"r":0.0,"b":0.0},"AddTrigDist":{"l":0.0,"t":0.0,"r":0.0,"b":0.0},"Flags":["Moveable","Connectable","SnapsToGridTopLeft"],"StringMap":[],"Transform":{"Rotation":0.0,"Flip":[]},"UID":16,"Name":"PositivePole1","Title":"","ToolTip":"","GIType":"GraphicsEllipseItemCfg","Alignment":"AlignCenter","SizePolicy":"Preferred","ConnectionDirection":"Out","RadiusX":10.0,"RadiusY":10.0,"BackgroundPainter":{"P2Type":"OT_P2DStyR","Ref":"Transparent"},"Outline":{"Width":0.0,"Style":"Solid","Cap":"Square","Join":"Bevel","Painter":{"P2Type":"OT_P2DStyR","Ref":"Transparent"}}},{"Position":{"x":50.0,"y":50.0},"Size.Min":{"w":0.0,"h":0.0},"Size.Max":{"w":1.7976931348623157e308,"h":1.7976931348623157e308},"Margin":{"l":0.0,"t":0.0,"r":0.0,"b":0.0},"AddTrigDist":{"l":0.0,"t":0.0,"r":0.0,"b":0.0},"Flags":["Moveable","SnapsToGridTopLeft"],"StringMap":[],"Transform":{"Rotation":0.0,"Flip":[]},"UID":17,"Name":"Text","Title":"","ToolTip":"","GIType":"GraphicsTextItemCfg","Alignment":"AlignCenter","SizePolicy":"Preferred","ConnectionDirection":"Out","Text":"Name","IsReference":true,"Font":{"Family":"Consolas","SizePx":12,"Bold":false,"Italic":false},"Style":{"Width":1.0,"Style":"Solid","Cap":"Square","Join":"Bevel","Painter":{"P2Type":"OT_P2DStyR","Ref":"GraphicsItem Foreground"}}}]}